w2widget/__init__.py
w2widget/doc2vec.py
w2widget/types.py
w2widget/utils.py
w2widget/widget.py
w2widget-0.0.3.dist-info/LICENSE
w2widget-0.0.3.dist-info/METADATA
w2widget-0.0.3.dist-info/WHEEL
w2widget-0.0.3.dist-info/top_level.txt
w2widget-0.0.3.dist-info/RECORD
