Metadata-Version: 2.1
Name: w2widget
Version: 0.0.3
Summary: Widget for exploring and sampling words from text data through w2v
Home-page: https://github.com/SODAS-KU/w2widget
Author: Tobias Gårdhus
Author-email: tpg@sodas.ku.dk
Project-URL: Bug Tracker, https://github.com/SODAS-KU/w2widget/issues
Classifier: Programming Language :: Python :: 3
Classifier: License :: OSI Approved :: MIT License
Classifier: Operating System :: OS Independent
Requires-Python: >=3.7
License-File: LICENSE
Requires-Dist: numpy (>=1.22.3)
Requires-Dist: openTSNE (>=0.6.0)
Requires-Dist: jupyter (>=1.0.0)
Requires-Dist: ipywidgets (==7.7.2)
Requires-Dist: plotly (>=5.6.0)
Requires-Dist: gensim (>=3.7.0)
Requires-Dist: nltk (>=3.6.7)
Requires-Dist: scikit-learn (>=1.0.2)
